yolov8face/__init__.py
yolov8face/yolo_model.py
yolov8face-0.1.1.dist-info/LICENSE
yolov8face-0.1.1.dist-info/METADATA
yolov8face-0.1.1.dist-info/WHEEL
yolov8face-0.1.1.dist-info/top_level.txt
yolov8face-0.1.1.dist-info/RECORD
