Metadata-Version: 2.1
Name: yolov8face
Version: 0.1.1
Summary: Yolov8face is a Python wrapper of Ultrlytics that simplifies the process of detecting faces in images using the yolov8n-face model. It takes care of model downloading, loading and postprocessing, allowing you to detect faces in images with just a few lines of code.
License-File: LICENSE
Requires-Dist: ultralytics
